moneyinpy.py
moneyinpy-1.2.1.dist-info/LICENSE
moneyinpy-1.2.1.dist-info/METADATA
moneyinpy-1.2.1.dist-info/WHEEL
moneyinpy-1.2.1.dist-info/top_level.txt
moneyinpy-1.2.1.dist-info/RECORD
