Metadata-Version: 2.1
Name: moneyinpy
Version: 1.2.1
Summary: A simple accounting program
Home-page: UNKNOWN
Author: Terry Hughes
Author-email: terryhugheskirkcudbright@yahoo.co.uk
License: UNKNOWN
Platform: UNKNOWN
Classifier: Programming Language :: Python :: 3
Classifier: License :: OSI Approved :: MIT License
Classifier: Operating System :: OS Independent
Requires-Python: >=3.6
